{
	"url": "http://www.sharingbuttons.org/w/images/a/ac/Sharingbuttons.png",
	"layout": {
		"http://www.sharingbuttons.org/w/images/5/53/Ask.png": [10, 10, 28, 28],
		"http://www.sharingbuttons.org/w/images/7/73/Bebo.png": [10, 48, 26, 64],
		"http://www.sharingbuttons.org/w/images/2/29/BlinkList.png": [10, 84, 28, 102],
		"http://www.sharingbuttons.org/w/images/8/89/BlogMarks.gif": [10, 122, 26, 138],
		"http://www.sharingbuttons.org/w/images/c/c1/Bloglines.png": [10, 158, 28, 176],
		"http://www.sharingbuttons.org/w/images/c/cd/Delicious.gif": [10, 196, 26, 212],
		"http://www.sharingbuttons.org/w/images/1/10/Digg.gif": [10, 232, 26, 246],
		"http://www.sharingbuttons.org/w/images/e/e2/Dzone.png": [10, 266, 26, 282],
		"http://www.sharingbuttons.org/w/images/6/66/Email.gif": [10, 302, 25, 314],
		"http://www.sharingbuttons.org/w/images/a/ad/Facebook.gif": [10, 334, 26, 350],
		"http://www.sharingbuttons.org/w/images/7/7a/Fark.gif": [10, 370, 25, 388],
		"http://www.sharingbuttons.org/w/images/f/fb/FriendFeed.png": [10, 408, 26, 424],
		"http://www.sharingbuttons.org/w/images/2/2e/Furl.png": [10, 444, 26, 461],
		"http://www.sharingbuttons.org/w/images/0/07/Garysguide.gif": [10, 481, 26, 497],
		"http://www.sharingbuttons.org/w/images/0/02/Google_Bookmarks.png": [10, 517, 28, 535],
		"http://www.sharingbuttons.org/w/images/4/4e/Buzz.png": [10, 555, 26, 271],
		"http://www.sharingbuttons.org/w/images/8/8c/Google_Calendar.gif": [10, 591, 26, 607],
		"http://www.sharingbuttons.org/w/images/6/68/Kaboodle.png": [10, 627, 26, 643],
		"http://www.sharingbuttons.org/w/images/a/ae/LinkedIn.png": [10, 663, 26, 679],
		"http://www.sharingbuttons.org/w/images/b/bc/Live.png": [10, 699, 26, 715],
		"http://www.sharingbuttons.org/w/images/a/a7/MisterWong.png": [10, 735, 26, 751],
		"http://www.sharingbuttons.org/w/images/f/f0/MySpace.gif": [10, 771, 26, 787],
		"http://www.sharingbuttons.org/w/images/2/2a/Netvouz.png": [10, 807, 26, 823],
		"http://www.sharingbuttons.org/w/images/a/a6/Newsvine.gif": [10, 843, 26, 859],
		"http://www.sharingbuttons.org/w/images/3/38/Reddit.gif": [10, 879, 28, 897],
		"http://www.sharingbuttons.org/w/images/b/b3/Simpy.png": [10, 917, 26, 933],
		"http://www.sharingbuttons.org/w/images/c/ce/Slashdot.gif": [10, 953, 27, 970],
		"http://www.sharingbuttons.org/w/images/e/ef/Spurl.gif": [10, 990, 26, 1006],
		"http://www.sharingbuttons.org/w/images/c/c4/Squidoo.png": [10, 1026, 28, 1044],
		"http://www.sharingbuttons.org/w/images/0/0c/StumbleUpon.gif": [10, 1064, 26, 1080],
		"http://www.sharingbuttons.org/w/images/d/d2/Stylehive.png": [10, 1100, 26, 1116],
		"http://www.sharingbuttons.org/w/images/f/f9/Surfpeople.png": [10, 1136, 26, 1152],
		"http://www.sharingbuttons.org/w/images/7/70/Technorati.png": [10, 1172, 18, 1190],
		"http://www.sharingbuttons.org/w/images/8/88/Twitter.gif": [10, 1210, 26, 1226],
		"http://www.sharingbuttons.org/w/images/1/16/Web2PDF.png": [10, 1246, 26, 1262],
		"http://www.sharingbuttons.org/w/images/c/c2/Wordpress.org.png": [10, 1282, 26, 1298],
		"http://www.sharingbuttons.org/w/images/8/8e/Yahoo%21_Bookmarks.gif": [10, 1318, 26, 1354]
	}
}
